{
"概念":"苹果概念，语音技术，智能音箱，Facebook概念，MSCI概念，独角兽概念，富士康概念，工业互联网，机器人概念，融资融券，深股通，...",
"财务":"三线蓝筹",
"分类":"大盘股",
"名称":"歌尔股份",
"code":"002241",
"全名":"歌尔股份有限公司",
"地域":"山东省",
"行业":"电子—电子制造",
"业务":"电声器件业务和电子配件业务",
"产品":"电声器件、电子配件",
"概念y":"深证成指-100%  声学-60%  虚拟现实-54%  骨传导-51%  意念支付-36%  智能手表-27%  智能穿戴-24%  智能音箱-22%  苹果产业链-19%  三星-19%  智能眼镜-17%  语音识别-15%  智能手机-15%  MEMS传感器-14%  潍坊保税区-13%  3D电视-11%  元器件-10%  传感器-10%  流媒体-8%  中小板指-6%  物联网-4%  移动互联网-4%  沪深300-3%  联想产业链-2%  深港通-2%  电视游戏-2%  游戏机-2%  WIN8-2%  智能识别-1%"}